pyfbsdk_stub_generator/__init__.py
pyfbsdk_stub_generator/module_types.py
pyfbsdk_stub_generator/native_generator.py
pyfbsdk_stub_generator/stub_generator.py
pyfbsdk_stub_generator/base_content/pyfbsdk.pyi
pyfbsdk_stub_generator/plugins/__init__.py
pyfbsdk_stub_generator/plugins/plugin.py
pyfbsdk_stub_generator/plugins/dunder_methods/__init__.py
pyfbsdk_stub_generator/plugins/dunder_methods/dunder_methods.py
pyfbsdk_stub_generator/plugins/fb_property/__init__.py
pyfbsdk_stub_generator/plugins/fb_property/fb_property_plugin.py
pyfbsdk_stub_generator/plugins/manual_documentation/__init__.py
pyfbsdk_stub_generator/plugins/manual_documentation/doc_bases.py
pyfbsdk_stub_generator/plugins/manual_documentation/plugin_manual_docs.py
pyfbsdk_stub_generator/plugins/manual_documentation/modules/__init__.py
pyfbsdk_stub_generator/plugins/manual_documentation/modules/pyfbsdk.py
pyfbsdk_stub_generator/plugins/online_documentation/__init__.py
pyfbsdk_stub_generator/plugins/online_documentation/plugin_online_documentation.py
pyfbsdk_stub_generator/plugins/online_documentation/documentation_scraper/__init__.py
pyfbsdk_stub_generator/plugins/online_documentation/documentation_scraper/documentation_cache.py
pyfbsdk_stub_generator/plugins/online_documentation/documentation_scraper/documentation_urls.py
pyfbsdk_stub_generator/plugins/online_documentation/documentation_scraper/page_parser.py
pyfbsdk_stub_generator/plugins/online_documentation/documentation_scraper/table_of_contents.py
pyfbsdk_stub_generator-2025.0.0.dist-info/LICENSE
pyfbsdk_stub_generator-2025.0.0.dist-info/METADATA
pyfbsdk_stub_generator-2025.0.0.dist-info/WHEEL
pyfbsdk_stub_generator-2025.0.0.dist-info/top_level.txt
pyfbsdk_stub_generator-2025.0.0.dist-info/RECORD
