Metadata-Version: 2.1
Name: pyfbsdk-stub-generator
Version: 2025.0.0
Summary: Generate pyfbsdk stub files for better intellisense when working with MotionBuilder
Home-page: https://github.com/nils-soderman/pyfbsdk-stub-generator
Author: Nils Soderman
License: MIT-0
Keywords: pyfbsdk,motionbuilder,mobu,autodesk,stub,stubfile,generator,gen
Classifier: Programming Language :: Python :: 3
Requires-Python: >=3.7
License-File: LICENSE
Requires-Dist: beautifulsoup4
Requires-Dist: markdownify
Requires-Dist: requests
Requires-Dist: Js2Py
